{
	"name" : "Stack Experience",
	"description" : "This module enables stack experience feature from WoG",
	"version" : "",
	"author" : "WoG Team",
	"contact" : "http://forum.vcmi.eu/index.php",
	"modType" : "Mechanics",
	"creatures" :
	[
		"config/castle_exp.json",
		"config/rampart_exp.json",
		"config/tower_exp.json",

		"config/necropolis_exp.json",
		"config/inferno_exp.json",
		"config/dungeon_exp.json",

		"config/stronghold_exp.json",
		"config/fortress_exp.json",
		"config/conflux_exp.json",

		"config/neutral_exp.json",
		"config/special_exp.json",

		"config/wogCreaturesStackExp.json",
		"config/level8CreaturesStackExp.json",
		"config/messengersStackExp.json",
		"config/godsStackExp.json"
	],
	"settings":
	{
		"modules":
		{
			"stackExperience": true
		}
	}
}
